xterm256_colors/__init__.py
xterm256_colors/_compat.py
xterm256_colors/colors.py
xterm256_colors/constants.py
xterm256_colors/py.typed
xterm256_colors/types.py
xterm256_colors/utils.py
xterm256_colors-0.1.4.dist-info/LICENSE
xterm256_colors-0.1.4.dist-info/WHEEL
xterm256_colors-0.1.4.dist-info/METADATA
xterm256_colors-0.1.4.dist-info/RECORD
