Metadata-Version: 2.1
Name: xterm256-colors
Version: 0.1.4
Summary: Handy utilities for interacting with xterm-256color terminal emulators
Home-page: https://github.com/theY4Kman/xterm256-colors
License: MIT
Author: Zach "theY4Kman" Kanzler
Author-email: they4kman@gmail.com
Requires-Python: >=3.9,<4.0
Classifier: License :: OSI Approved :: MIT License
Classifier: Programming Language :: Python :: 3
Classifier: Programming Language :: Python :: 3.10
Classifier: Programming Language :: Python :: 3.9
Provides-Extra: colormath
Requires-Dist: colormath (>=3.0.0,<4.0.0); extra == "colormath"
Project-URL: Repository, https://github.com/theY4Kman/xterm256-colors
